adjudicator/Cache.py
adjudicator/Executor.py
adjudicator/HashSupport.py
adjudicator/HashSupport_test.py
adjudicator/Params.py
adjudicator/Params_test.py
adjudicator/RuleEngine.py
adjudicator/RuleEngine_test.py
adjudicator/RuleGraph.py
adjudicator/RuleGraph_test.py
adjudicator/Signature.py
adjudicator/__init__.py
adjudicator/errors.py
adjudicator/py.typed
adjudicator/rule.py
adjudicator/rule_test.py
python_adjudicator-0.5.1.dist-info/METADATA
python_adjudicator-0.5.1.dist-info/WHEEL
python_adjudicator-0.5.1.dist-info/licenses/LICENSE
python_adjudicator-0.5.1.dist-info/RECORD
