Metadata-Version: 2.4
Name: python-adjudicator
Version: 0.5.1
Project-URL: Bug Tracker, https://github.com/NiklasRosenstein/python-adjudicator/issues
Project-URL: Homepage, https://github.com/NiklasRosenstein/python-adjudicator
Project-URL: Repository, https://github.com/NiklasRosenstein/python-adjudicator
Author-email: Niklas Rosenstein <rosensteinniklas@gmail.com>
License-Expression: MIT
License-File: LICENSE
Requires-Python: >=3.10
Requires-Dist: networkx>=3.1
Requires-Dist: typeapi<3,>=2.1.0
